gbk_to_sqlite/__init__.py
gbk_to_sqlite/cli.py
gbk_to_sqlite/core.py
gbk_to_sqlite/models.py
gbk_to_sqlite-0.1.0.dist-info/METADATA
gbk_to_sqlite-0.1.0.dist-info/WHEEL
gbk_to_sqlite-0.1.0.dist-info/entry_points.txt
gbk_to_sqlite-0.1.0.dist-info/licenses/LICENSE
gbk_to_sqlite-0.1.0.dist-info/RECORD
