Metadata-Version: 2.4
Name: gbk-to-sqlite
Version: 0.1.0
Summary: Convert GenBank files to SQLite databases
Author-email: Austin Davis-Richardson <hello@agdr.org>
License: MIT
License-File: LICENSE
Classifier: Development Status :: 4 - Beta
Classifier: Intended Audience :: Science/Research
Classifier: License :: OSI Approved :: MIT License
Classifier: Programming Language :: Python :: 3
Classifier: Programming Language :: Python :: 3.11
Classifier: Topic :: Scientific/Engineering :: Bio-Informatics
Requires-Python: >=3.11
Requires-Dist: gb-io>=0.3.6
Requires-Dist: peewee>=3.18.1
Requires-Dist: tqdm>=4.67.1
Provides-Extra: dev
Requires-Dist: py-spy>=0.4.0; extra == 'dev'
Requires-Dist: pytest>=8.4.0; extra == 'dev'
